[{"def":"a","capital":["╔═╗","╠═╣","╩ ╩"],"small":["┌─┐","├─┤","┴ ┴"]},{"def":"b","capital":["╔╗ ","╠╩╗","╚═╝"],"small":["┌┐ ","├┴┐","└─┘"]},{"def":"c","capital":["╔═╗","║  ","╚═╝"],"small":["┌─┐","│  ","└─┘"]},{"def":"d","capital":["╔╦╗"," ║║","═╩╝"],"small":["┌┬┐"," ││","─┴┘"]},{"def":"e","capital":["╔═╗","║╣ ","╚═╝"],"small":["┌─┐","├┤ ","└─┘"]},{"def":"f","capital":["╔═╗","╠╣ ","╚  "],"small":["┌─┐","├┤ ","└  "]},{"def":"g","capital":["╔═╗","║ ╦","╚═╝"],"small":["┌─┐","│ ┬","└─┘"]},{"def":"h","capital":["╦ ╦","╠═╣","╩ ╩"],"small":["┬ ┬","├─┤","┴ ┴"]},{"def":"i","capital":[" ╦ "," ║ "," ╩ "],"small":[" ┬ "," │ "," ┴ "]},{"def":"j","capital":[" ╦"," ║","╚╝"],"small":[" ┬"," │","└┘"]},{"def":"k","capital":["╦╔═","╠╩╗","╩ ╩"],"small":["┬┌─","├┴┐","┴ ┴"]},{"def":"l","capital":["╦  ","║  ","╩═╝"],"small":["┬  ","│  ","┴─┘"]},{"def":"m","capital":["╔╦╗","║║║","╩ ╩"],"small":["┌┬┐","│││","┴ ┴"]},{"def":"n","capital":["╔╗╔","║║║","╝╚╝"],"small":["┌┐┌","│││","┘└┘"]},{"def":"o","capital":["╔═╗","║ ║","╚═╝"],"small":["┌─┐","│ │","└─┘"]},{"def":"p","capital":["╔═╗","╠═╝","╩  "],"small":["┌─┐","├─┘","┴  "]},{"def":"q","capital":["╔═╗ ","║═╬╗","╚═╝╚"],"small":["┌─┐ ","│─┼┐","└─┘└"]},{"def":"r","capital":["╦═╗","╠╦╝","╩╚═"],"small":["┬─┐","├┬┘","┴└─"]},{"def":"s","capital":["╔═╗","╚═╗","╚═╝"],"small":["┌─┐","└─┐","└─┘"]},{"def":"t","capital":["╔╦╗"," ║ "," ╩ "],"small":["┌┬┐"," │ "," ┴ "]},{"def":"u","capital":["╦ ╦","║ ║","╚═╝"],"small":["┬ ┬","│ │","└─┘"]},{"def":"v","capital":["╦  ╦","╚╗╔╝"," ╚╝ "],"small":["┬  ┬","└┐┌┘"," └┘ "]},{"def":"w","capital":["╦ ╦","║║║","╚╩╝"],"small":["┬ ┬","│││","└┴┘"]},{"def":"x","capital":["═╗ ╦","╔╩╦╝","╩ ╚═"],"small":["─┐ ┬","┌┴┬┘","┴ └─"]},{"def":"y","capital":["╦ ╦","╚╦╝"," ╩ "],"small":["┬ ┬","└┬┘"," ┴ "]},{"def":"z","capital":["╔═╗","╔═╝","╚═╝"],"small":["┌─┐","┌─┘","└─┘"]}]